digital_clock.v
// digital_clock.v
// 24-hour clock: hr:min:sec
// hr is 0..23 (5 bits), min/sec are 0..59 (6 bits)

module digital_clock #(
    parameter integer DIVIDER = 50_000_000  // for 50 MHz input clock -> 1 second ticks
)(
    input  wire clk,
    input  wire reset,       // active-high synchronous reset
    output reg [5:0] sec,    // 0..59
    output reg [5:0] min,    // 0..59
    output reg [4:0] hr      // 0..23
);

    // width must hold DIVIDER value
    localparam integer CW = $clog2(DIVIDER+1);
    reg [CW-1:0] clk_div;

    // 1 Hz pulse (or faster for simulation if DIVIDER small)
    wire tick = (clk_div == DIVIDER-1);

    // clock divider
    always @(posedge clk) begin
        if (reset) begin
            clk_div <= 0;
        end else begin
            if (tick)
                clk_div <= 0;
            else
                clk_div <= clk_div + 1;
        end
    end

    // time counters
    always @(posedge clk) begin
        if (reset) begin
            sec <= 0;
            min <= 0;
            hr  <= 0;
        end else if (tick) begin
            if (sec == 59) begin
                sec <= 0;
                if (min == 59) begin
                    min <= 0;
                    if (hr == 23)
                        hr <= 0;
                    else
                        hr <= hr + 1;
                end else begin
                    min <= min + 1;
                end
            end else begin
                sec <= sec + 1;
            end
        end
    end

endmodule

tb_digital_clock.v
// tb_digital_clock.v
`timescale 1ns/1ps

module tb_digital_clock;

    // Testbench clock freq (for simulation only)
    reg clk = 0;
    reg reset = 1;

    // Use small DIVIDER for fast sim
    localparam integer DIV = 10; // tick every 10 tb clock cycles (~fast)
    
    wire [5:0] sec;
    wire [5:0] min;
    wire [4:0] hr;

    // instantiate DUT
    digital_clock #(.DIVIDER(DIV)) dut (
        .clk(clk),
        .reset(reset),
        .sec(sec),
        .min(min),
        .hr(hr)
    );

    // generate clock: 10 ns period (100 MHz) - arbitrary for TB
    always #5 clk = ~clk;

    // VCD dump for GTKWave
    initial begin
        $dumpfile("dump.vcd");
        $dumpvars(0, tb_digital_clock);
    end

    // reset sequence
    initial begin
        reset = 1;
        #20;
        reset = 0;
    end

    // print every second update (on tick boundary we expect change)
    reg [5:0] last_sec = 6'hFF;
    reg [5:0] last_min = 6'hFF;
    reg [4:0] last_hr  = 5'h1F;

    always @(posedge clk) begin
        // display when any of the outputs change
        if ({sec,min,hr} != {last_sec,last_min,last_hr}) begin
            $display("T=%0t ns -> %02d:%02d:%02d", $time, hr, min, sec);
            last_sec = sec;
            last_min = min;
            last_hr = hr;
        end
    end

    // end simulation after some time
    initial begin
        #2000; // adjust to run longer if you want
        $display("Testbench finished");
        $finish;
    end

endmodule

dump.vcd
$date
	Thu Oct 16 05:18:13 2025
$end
$version
	Icarus Verilog
$end
$timescale
	1ps
$end
$scope module tb_digital_clock $end
$var wire 6 ! sec [5:0] $end
$var wire 6 " min [5:0] $end
$var wire 5 # hr [4:0] $end
$var parameter 32 $ DIV $end
$var reg 1 % clk $end
$var reg 5 & last_hr [4:0] $end
$var reg 6 ' last_min [5:0] $end
$var reg 6 ( last_sec [5:0] $end
$var reg 1 ) reset $end
$scope module dut $end
$var wire 1 % clk $end
$var wire 1 ) reset $end
$var wire 1 * tick $end
$var parameter 32 + CW $end
$var parameter 32 , DIVIDER $end
$var reg 4 - clk_div [3:0] $end
$var reg 5 . hr [4:0] $end
$var reg 6 / min [5:0] $end
$var reg 6 0 sec [5:0] $end
$upscope $end
$upscope $end
$enddefinitions $end
$comment Show the parameter values. $end
$dumpall
b1010 ,
b100 +
b1010 $
$end
#0
$dumpvars
bx 0
bx /
bx .
bx -
x*
1)
b111111 (
b111111 '
b11111 &
0%
bx #
bx "
bx !
$end
#5000
0*
b0 -
b0 #
b0 .
b0 "
b0 /
b0 !
b0 0
1%
#10000
0%
#15000
b0 &
b0 '
b0 (
1%
#20000
0%
0)
#25000
b1 -
1%
#30000
0%
#35000
b10 -
1%
#40000
0%
#45000
b11 -
1%
#50000
0%
#55000
b100 -
1%
#60000
0%
#65000
b101 -
1%
#70000
0%
#75000
b110 -
1%
#80000
0%
#85000
b111 -
1%
#90000
0%
#95000
b1000 -
1%
#100000
0%
#105000
1*
b1001 -
1%
#110000
0%
#115000
b1 !
b1 0
0*
b0 -
1%
#120000
0%
#125000
b1 -
b1 (
1%
#130000
0%
#135000
b10 -
1%
#140000
0%
#145000
b11 -
1%
#150000
0%
#155000
b100 -
1%
#160000
0%
#165000
b101 -
1%
#170000
0%
#175000
b110 -
1%
#180000
0%
#185000
b111 -
1%
#190000
0%
#195000
b1000 -
1%
#200000
0%
#205000
1*
b1001 -
1%
#210000
0%
#215000
b10 !
b10 0
0*
b0 -
1%
#220000
0%
#225000
b1 -
b10 (
1%
#230000
0%
#235000
b10 -
1%
#240000
0%
#245000
b11 -
1%
#250000
0%
#255000
b100 -
1%
#260000
0%
#265000
b101 -
1%
#270000
0%
#275000
b110 -
1%
#280000
0%
#285000
b111 -
1%
#290000
0%
#295000
b1000 -
1%
#300000
0%
#305000
1*
b1001 -
1%
#310000
0%
#315000
b11 !
b11 0
0*
b0 -
1%
#320000
0%
#325000
b1 -
b11 (
1%
#330000
0%
#335000
b10 -
1%
#340000
0%
#345000
b11 -
1%
#350000
0%
#355000
b100 -
1%
#360000
0%
#365000
b101 -
1%
#370000
0%
#375000
b110 -
1%
#380000
0%
#385000
b111 -
1%
#390000
0%
#395000
b1000 -
1%
#400000
0%
#405000
1*
b1001 -
1%
#410000
0%
#415000
b100 !
b100 0
0*
b0 -
1%
#420000
0%
#425000
b1 -
b100 (
1%
#430000
0%
#435000
b10 -
1%
#440000
0%
#445000
b11 -
1%
#450000
0%
#455000
b100 -
1%
#460000
0%
#465000
b101 -
1%
#470000
0%
#475000
b110 -
1%
#480000
0%
#485000
b111 -
1%
#490000
0%
#495000
b1000 -
1%
#500000
0%
#505000
1*
b1001 -
1%
#510000
0%
#515000
b101 !
b101 0
0*
b0 -
1%
#520000
0%
#525000
b1 -
b101 (
1%
#530000
0%
#535000
b10 -
1%
#540000
0%
#545000
b11 -
1%
#550000
0%
#555000
b100 -
1%
#560000
0%
#565000
b101 -
1%
#570000
0%
#575000
b110 -
1%
#580000
0%
#585000
b111 -
1%
#590000
0%
#595000
b1000 -
1%
#600000
0%
#605000
1*
b1001 -
1%
#610000
0%
#615000
b110 !
b110 0
0*
b0 -
1%
#620000
0%
#625000
b1 -
b110 (
1%
#630000
0%
#635000
b10 -
1%
#640000
0%
#645000
b11 -
1%
#650000
0%
#655000
b100 -
1%
#660000
0%
#665000
b101 -
1%
#670000
0%
#675000
b110 -
1%
#680000
0%
#685000
b111 -
1%
#690000
0%
#695000
b1000 -
1%
#700000
0%
#705000
1*
b1001 -
1%
#710000
0%
#715000
b111 !
b111 0
0*
b0 -
1%
#720000
0%
#725000
b1 -
b111 (
1%
#730000
0%
#735000
b10 -
1%
#740000
0%
#745000
b11 -
1%
#750000
0%
#755000
b100 -
1%
#760000
0%
#765000
b101 -
1%
#770000
0%
#775000
b110 -
1%
#780000
0%
#785000
b111 -
1%
#790000
0%
#795000
b1000 -
1%
#800000
0%
#805000
1*
b1001 -
1%
#810000
0%
#815000
b1000 !
b1000 0
0*
b0 -
1%
#820000
0%
#825000
b1 -
b1000 (
1%
#830000
0%
#835000
b10 -
1%
#840000
0%
#845000
b11 -
1%
#850000
0%
#855000
b100 -
1%
#860000
0%
#865000
b101 -
1%
#870000
0%
#875000
b110 -
1%
#880000
0%
#885000
b111 -
1%
#890000
0%
#895000
b1000 -
1%
#900000
0%
#905000
1*
b1001 -
1%
#910000
0%
#915000
b1001 !
b1001 0
0*
b0 -
1%
#920000
0%
#925000
b1 -
b1001 (
1%
#930000
0%
#935000
b10 -
1%
#940000
0%
#945000
b11 -
1%
#950000
0%
#955000
b100 -
1%
#960000
0%
#965000
b101 -
1%
#970000
0%
#975000
b110 -
1%
#980000
0%
#985000
b111 -
1%
#990000
0%
#995000
b1000 -
1%
#1000000
0%
#1005000
1*
b1001 -
1%
#1010000
0%
#1015000
b1010 !
b1010 0
0*
b0 -
1%
#1020000
0%
#1025000
b1 -
b1010 (
1%
#1030000
0%
#1035000
b10 -
1%
#1040000
0%
#1045000
b11 -
1%
#1050000
0%
#1055000
b100 -
1%
#1060000
0%
#1065000
b101 -
1%
#1070000
0%
#1075000
b110 -
1%
#1080000
0%
#1085000
b111 -
1%
#1090000
0%
#1095000
b1000 -
1%
#1100000
0%
#1105000
1*
b1001 -
1%
#1110000
0%
#1115000
b1011 !
b1011 0
0*
b0 -
1%
#1120000
0%
#1125000
b1 -
b1011 (
1%
#1130000
0%
#1135000
b10 -
1%
#1140000
0%
#1145000
b11 -
1%
#1150000
0%
#1155000
b100 -
1%
#1160000
0%
#1165000
b101 -
1%
#1170000
0%
#1175000
b110 -
1%
#1180000
0%
#1185000
b111 -
1%
#1190000
0%
#1195000
b1000 -
1%
#1200000
0%
#1205000
1*
b1001 -
1%
#1210000
0%
#1215000
b1100 !
b1100 0
0*
b0 -
1%
#1220000
0%
#1225000
b1 -
b1100 (
1%
#1230000
0%
#1235000
b10 -
1%
#1240000
0%
#1245000
b11 -
1%
#1250000
0%
#1255000
b100 -
1%
#1260000
0%
#1265000
b101 -
1%
#1270000
0%
#1275000
b110 -
1%
#1280000
0%
#1285000
b111 -
1%
#1290000
0%
#1295000
b1000 -
1%
#1300000
0%
#1305000
1*
b1001 -
1%
#1310000
0%
#1315000
b1101 !
b1101 0
0*
b0 -
1%
#1320000
0%
#1325000
b1 -
b1101 (
1%
#1330000
0%
#1335000
b10 -
1%
#1340000
0%
#1345000
b11 -
1%
#1350000
0%
#1355000
b100 -
1%
#1360000
0%
#1365000
b101 -
1%
#1370000
0%
#1375000
b110 -
1%
#1380000
0%
#1385000
b111 -
1%
#1390000
0%
#1395000
b1000 -
1%
#1400000
0%
#1405000
1*
b1001 -
1%
#1410000
0%
#1415000
b1110 !
b1110 0
0*
b0 -
1%
#1420000
0%
#1425000
b1 -
b1110 (
1%
#1430000
0%
#1435000
b10 -
1%
#1440000
0%
#1445000
b11 -
1%
#1450000
0%
#1455000
b100 -
1%
#1460000
0%
#1465000
b101 -
1%
#1470000
0%
#1475000
b110 -
1%
#1480000
0%
#1485000
b111 -
1%
#1490000
0%
#1495000
b1000 -
1%
#1500000
0%
#1505000
1*
b1001 -
1%
#1510000
0%
#1515000
b1111 !
b1111 0
0*
b0 -
1%
#1520000
0%
#1525000
b1 -
b1111 (
1%
#1530000
0%
#1535000
b10 -
1%
#1540000
0%
#1545000
b11 -
1%
#1550000
0%
#1555000
b100 -
1%
#1560000
0%
#1565000
b101 -
1%
#1570000
0%
#1575000
b110 -
1%
#1580000
0%
#1585000
b111 -
1%
#1590000
0%
#1595000
b1000 -
1%
#1600000
0%
#1605000
1*
b1001 -
1%
#1610000
0%
#1615000
b10000 !
b10000 0
0*
b0 -
1%
#1620000
0%
#1625000
b1 -
b10000 (
1%
#1630000
0%
#1635000
b10 -
1%
#1640000
0%
#1645000
b11 -
1%
#1650000
0%
#1655000
b100 -
1%
#1660000
0%
#1665000
b101 -
1%
#1670000
0%
#1675000
b110 -
1%
#1680000
0%
#1685000
b111 -
1%
#1690000
0%
#1695000
b1000 -
1%
#1700000
0%
#1705000
1*
b1001 -
1%
#1710000
0%
#1715000
b10001 !
b10001 0
0*
b0 -
1%
#1720000
0%
#1725000
b1 -
b10001 (
1%
#1730000
0%
#1735000
b10 -
1%
#1740000
0%
#1745000
b11 -
1%
#1750000
0%
#1755000
b100 -
1%
#1760000
0%
#1765000
b101 -
1%
#1770000
0%
#1775000
b110 -
1%
#1780000
0%
#1785000
b111 -
1%
#1790000
0%
#1795000
b1000 -
1%
#1800000
0%
#1805000
1*
b1001 -
1%
#1810000
0%
#1815000
b10010 !
b10010 0
0*
b0 -
1%
#1820000
0%
#1825000
b1 -
b10010 (
1%
#1830000
0%
#1835000
b10 -
1%
#1840000
0%
#1845000
b11 -
1%
#1850000
0%
#1855000
b100 -
1%
#1860000
0%
#1865000
b101 -
1%
#1870000
0%
#1875000
b110 -
1%
#1880000
0%
#1885000
b111 -
1%
#1890000
0%
#1895000
b1000 -
1%
#1900000
0%
#1905000
1*
b1001 -
1%
#1910000
0%
#1915000
b10011 !
b10011 0
0*
b0 -
1%
#1920000
0%
#1925000
b1 -
b10011 (
1%
#1930000
0%
#1935000
b10 -
1%
#1940000
0%
#1945000
b11 -
1%
#1950000
0%
#1955000
b100 -
1%
#1960000
0%
#1965000
b101 -
1%
#1970000
0%
#1975000
b110 -
1%
#1980000
0%
#1985000
b111 -
1%
#1990000
0%
#1995000
b1000 -
1%
